pak8/__init__.py
pak8/app/__init__.py
pak8/app/base.py
pak8/app/airflow/__init__.py
pak8/app/airflow/airflow_app.py
pak8/app/devbox/__init__.py
pak8/app/devbox/devbox_app.py
pak8/app/elastic/__init__.py
pak8/app/elastic/elastic_app.py
pak8/app/postgres/__init__.py
pak8/app/postgres/postgres_app.py
pak8/conf/__init__.py
pak8/conf/constants.py
pak8/docker/__init__.py
pak8/docker/docker_pak8.py
pak8/docker/docker_utils.py
pak8/docker/clients/__init__.py
pak8/docker/clients/docker_pak8_client.py
pak8/docker/conf/__init__.py
pak8/docker/conf/docker_pak8_conf.py
pak8/docker/enums/__init__.py
pak8/docker/enums/docker_enums.py
pak8/docker/exceptions/__init__.py
pak8/docker/exceptions/docker_exceptions.py
pak8/docker/resources/__init__.py
pak8/docker/resources/container.py
pak8/docker/resources/docker_resource_base.py
pak8/docker/resources/docker_resource_group.py
pak8/docker/resources/docker_resource_types.py
pak8/docker/resources/image.py
pak8/docker/resources/network.py
pak8/docker/resources/volume.py
pak8/enums/__init__.py
pak8/enums/pak8_enums.py
pak8/exceptions/__init__.py
pak8/exceptions/pak8_exceptions.py
pak8/gcp/__init__.py
pak8/gcp/gcp_pak8.py
pak8/gcp/api/__init__.py
pak8/gcp/api/gke/__init__.py
pak8/gcp/api/gke/gke_cluster.py
pak8/gcp/clients/__init__.py
pak8/gcp/clients/cloudsql_pak8_client.py
pak8/gcp/clients/gcs_pak8_client.py
pak8/gcp/clients/gke_pak8_client.py
pak8/gcp/conf/__init__.py
pak8/gcp/conf/gcp_pak8_conf.py
pak8/gcp/enums/__init__.py
pak8/gcp/enums/gcp_enums.py
pak8/gcp/exceptions/__init__.py
pak8/gcp/exceptions/gcp_exceptions.py
pak8/gcp/resources/__init__.py
pak8/gcp/resources/cloudsql.py
pak8/gcp/resources/gcs.py
pak8/gcp/resources/gke.py
pak8/k8s/__init__.py
pak8/k8s/k8s_utils.py
pak8/k8s/api/__init__.py
pak8/k8s/api/k8s_api.py
pak8/k8s/api/k8s_resource_group.py
pak8/k8s/api/kubeconfig.py
pak8/k8s/api/apiextensions_k8s_io/__init__.py
pak8/k8s/api/apiextensions_k8s_io/v1beta1/__init__.py
pak8-0.1.dist-info/METADATA
pak8-0.1.dist-info/WHEEL
pak8-0.1.dist-info/top_level.txt
pak8-0.1.dist-info/RECORD
