Metadata-Version: 2.1
Name: pak8
Version: 0.1
Summary: UNKNOWN
Home-page: UNKNOWN
Author: UNKNOWN
Author-email: UNKNOWN
License: UNKNOWN
Platform: UNKNOWN
Requires-Dist: attrs (==21.2.0)
Requires-Dist: black (==21.9b0)
Requires-Dist: cachetools (==4.2.4)
Requires-Dist: certifi (==2021.10.8)
Requires-Dist: cffi (==1.14.6)
Requires-Dist: charset-normalizer (==2.0.7)
Requires-Dist: click (==8.0.3)
Requires-Dist: colorama (==0.4.4)
Requires-Dist: commonmark (==0.9.1)
Requires-Dist: deprecated (==1.2.13)
Requires-Dist: docker (==5.0.3)
Requires-Dist: google-api-core[grpc] (==2.1.0)
Requires-Dist: google-api-python-client (==2.25.0)
Requires-Dist: google-auth (==2.3.0)
Requires-Dist: google-auth-httplib2 (==0.1.0)
Requires-Dist: google-cloud-container (==2.9.0)
Requires-Dist: google-cloud-core (==2.1.0)
Requires-Dist: google-cloud-storage (==1.42.3)
Requires-Dist: google-crc32c (==1.3.0)
Requires-Dist: google-resumable-media (==2.0.3)
Requires-Dist: googleapis-common-protos[grpc] (==1.53.0)
Requires-Dist: grpc-google-iam-v1 (==0.12.3)
Requires-Dist: grpcio (==1.41.0)
Requires-Dist: httplib2 (==0.20.1)
Requires-Dist: idna (==3.2)
Requires-Dist: importlib-metadata (==4.8.1)
Requires-Dist: iniconfig (==1.1.1)
Requires-Dist: isort (==5.9.3)
Requires-Dist: kubernetes (==18.20.0)
Requires-Dist: libcst (==0.3.21)
Requires-Dist: mypy (==0.910)
Requires-Dist: mypy-extensions (==0.4.3)
Requires-Dist: oauthlib (==3.1.1)
Requires-Dist: packaging (==21.0)
Requires-Dist: pathspec (==0.9.0)
Requires-Dist: platformdirs (==2.4.0)
Requires-Dist: pluggy (==1.0.0)
Requires-Dist: proto-plus (==1.19.5)
Requires-Dist: protobuf (==3.18.1)
Requires-Dist: py (==1.10.0)
Requires-Dist: pyasn1 (==0.4.8)
Requires-Dist: pyasn1-modules (==0.2.8)
Requires-Dist: pycparser (==2.20)
Requires-Dist: pydantic (==1.8.2)
Requires-Dist: pygithub (==1.55)
Requires-Dist: pygments (==2.10.0)
Requires-Dist: pyjwt (==2.2.0)
Requires-Dist: pynacl (==1.4.0)
Requires-Dist: pyparsing (==2.4.7)
Requires-Dist: pytest (==6.2.5)
Requires-Dist: python-dateutil (==2.8.2)
Requires-Dist: pyyaml (==5.4.1)
Requires-Dist: regex (==2021.10.8)
Requires-Dist: requests (==2.26.0)
Requires-Dist: requests-oauthlib (==1.3.0)
Requires-Dist: rich (==10.12.0)
Requires-Dist: rsa (==4.7.2)
Requires-Dist: shellingham (==1.4.0)
Requires-Dist: six (==1.16.0)
Requires-Dist: toml (==0.10.2)
Requires-Dist: tomli (==1.2.1)
Requires-Dist: typed-ast (==1.4.3)
Requires-Dist: typer[all] (==0.4.0)
Requires-Dist: types-pyyaml (==5.4.11)
Requires-Dist: typing-extensions (==3.10.0.2)
Requires-Dist: typing-inspect (==0.7.1)
Requires-Dist: uritemplate (==3.0.1)
Requires-Dist: urllib3 (==1.26.7)
Requires-Dist: websocket-client (==1.2.1)
Requires-Dist: wrapt (==1.13.1)
Requires-Dist: zipp (==3.6.0)
